snewpy/__init__.py
snewpy/_model_downloader.py
snewpy/flavor_transformation.py
snewpy/flux.py
snewpy/from_snowglobes.py
snewpy/neutrino.py
snewpy/rate_calculator.py
snewpy/run_snowglobes.py
snewpy/snowglobes.py
snewpy/snowglobes_interface.py
snewpy/to_snowglobes.py
snewpy/models/__init__.py
snewpy/models/base.py
snewpy/models/ccsn.py
snewpy/models/ccsn_loaders.py
snewpy/models/extended.py
snewpy/models/model_files.yml
snewpy/models/presn.py
snewpy/models/presn_loaders.py
snewpy/models/registry_model.py
snewpy/test/__init__.py
snewpy/test/_rate_crosscheck_table.py
snewpy/test/simplerate_integrationtest.py
snewpy/test/test_00_init.py
snewpy/test/test_01_registry.py
snewpy/test/test_02_models.py
snewpy/test/test_03_neutrino.py
snewpy/test/test_04_xforms.py
snewpy/test/test_05_snowglobes.py
snewpy/test/test_flux_container.py
snewpy/test/test_presn_rates.py
snewpy/test/test_rate_calculation.py
snewpy-1.6.dist-info/licenses/LICENSE
snewpy-1.6.dist-info/METADATA
snewpy-1.6.dist-info/WHEEL
snewpy-1.6.dist-info/top_level.txt
snewpy-1.6.dist-info/RECORD
