Metadata-Version: 2.4
Name: snewpy
Version: 1.6
Summary: A Python package for working with supernova neutrinos
Author-email: SNEWS Collaboration <snews2.0@lists.bnl.gov>
License: BSD
Project-URL: Homepage, https://github.com/SNEWS2/snewpy
Project-URL: Bug Tracker, https://github.com/SNEWS2/snewpy/issues
Requires-Python: >=3.9
License-File: LICENSE
Requires-Dist: numpy
Requires-Dist: scipy
Requires-Dist: astropy>=4.3
Requires-Dist: pandas
Requires-Dist: tqdm
Requires-Dist: matplotlib
Requires-Dist: h5py
Requires-Dist: requests
Requires-Dist: pyyaml
Requires-Dist: snowglobes_data==1.3.2
Provides-Extra: dev
Requires-Dist: hypothesis; extra == "dev"
Requires-Dist: pytest; extra == "dev"
Provides-Extra: docs
Requires-Dist: numpydoc; extra == "docs"
Requires-Dist: nbsphinx; extra == "docs"
Requires-Dist: ipykernel; extra == "docs"
Requires-Dist: tqdm[notebook]; extra == "docs"
Dynamic: license-file
